LICENSE
MANIFEST.in
README.rst
setup.cfg
setup.py
django_select2_tags.egg-info/PKG-INFO
django_select2_tags.egg-info/SOURCES.txt
django_select2_tags.egg-info/dependency_links.txt
django_select2_tags.egg-info/not-zip-safe
django_select2_tags.egg-info/top_level.txt
select2_tags/__init__.py
select2_tags/forms.py
tests/__init__.py
tests/forms.py
tests/models.py
tests/settings.py
tests/test_forms.py