Metadata-Version: 1.1
Name: django-select2-tags
Version: 0.0.1
Summary: Django forms that support new items entered using Select2 with tags enabled
Home-page: https://github.com/jessamynsmith/django-select2-tags
Author: Jessamyn Smith
Author-email: jessamyn.smith.com
License: UNKNOWN
Download-URL: https://github.com/jessamynsmith/django-select2-tags/archive/0.1.tar.gz
Platform: UNKNOWN
Classifier: Environment :: Web Environment
Classifier: Intended Audience :: Developers
Classifier: Operating System :: OS Independent
Classifier: Programming Language :: Python
Classifier: Framework :: Django
